django_recurring-1.3.2.dist-info/licenses/LICENSE
recurring/__init__.py
recurring/admin.py
recurring/apps.py
recurring/forms.py
recurring/models.py
recurring/settings_test.py
recurring/widgets.py
recurring/management/commands/calculate_occurrences.py
recurring/migrations/0001_initial.py
recurring/migrations/0002_alter_calendarentry_description_and_more.py
recurring/migrations/0003_calendarentry_first_occurrence_and_more.py
recurring/migrations/0004_calendarentry_created_at_calendarentry_updated_at.py
recurring/migrations/__init__.py
recurring/static/admin/css/calendar_entry_widget.css
recurring/static/admin/js/calendar_entry_widget.js
recurring/static/admin/js/vendor/luxon-3.5.0.min.js
recurring/templates/admin/recurring/calendar_entry_widget.html
django_recurring-1.3.2.dist-info/METADATA
django_recurring-1.3.2.dist-info/WHEEL
django_recurring-1.3.2.dist-info/top_level.txt
django_recurring-1.3.2.dist-info/RECORD
