Metadata-Version: 2.4
Name: django_recurring
Version: 1.3.2
Summary: Complex recurring datetimes in django using dateutil rrulesets, exportable as ical files
Author-email: Boosh <boosh@example.com>
Maintainer-email: Boosh <boosh@example.com>
License: MIT license
Project-URL: bugs, https://github.com/boosh/django_recurring/issues
Project-URL: changelog, https://github.com/boosh/django_recurring/blob/master/changelog.md
Project-URL: homepage, https://github.com/boosh/django_recurring
License-File: LICENSE
Requires-Dist: icalendar==6.0.0
Requires-Dist: python-dateutil<3.0.0,>=2.0.0
Provides-Extra: dev
Requires-Dist: coverage; extra == "dev"
Requires-Dist: mypy; extra == "dev"
Requires-Dist: pytest; extra == "dev"
Requires-Dist: pytest-django; extra == "dev"
Requires-Dist: django; extra == "dev"
Requires-Dist: ruff; extra == "dev"
Requires-Dist: pre-commit; extra == "dev"
Requires-Dist: build; extra == "dev"
Requires-Dist: twine; extra == "dev"
Requires-Dist: sphinx==8.0.2; extra == "dev"
Requires-Dist: watchdog==5.0.3; extra == "dev"
Requires-Dist: aider-chat; extra == "dev"
Dynamic: license-file
